<?xml version="1.0" encoding="UTF-8" standalone="no"?><?xml-stylesheet type="text/xml" href="test.xsl"?><carnet><id>1</id><fechaexp>01-02-2025</fechaexp><expedidoen>parada Gijon</expedidoen><peregrino><nombre>Daniel</nombre><nacionalidad>España</nacionalidad></peregrino><hoy>18-02-2025</hoy><distanciatotal>10,0</distanciatotal><paradas><parada><orden>1</orden><nombre>Gijon</nombre><region>A</region></parada><parada><orden>2</orden><nombre>Oviedo</nombre><region>A</region></parada><parada><orden>3</orden><nombre>Aviles</nombre><region>A</region></parada></paradas><estancias><estancia><id>1</id><fecha>01-02-2025</fecha><parada>Oviedo</parada><vip/></estancia><estancia><id>2</id><fecha>01-02-2025</fecha><parada>Aviles</parada><vip/></estancia></estancias></carnet>